[
  {
    "nome": "Eloá",
    "sobrenome": "Giovanna Silveira",
    "empresa": "EBAC",
    "endereco": "Rua Argentina",
    "numero": "594",
    "pais": "Brasil",
    "cidade": "Teresópolis",
    "estado": "Rio de Janeiro",
    "cep": "25977-360",
    "telefone": "(21) 99337-1656",
    "email": "eloagiovannasilveira__eloagiovannasilveira@a.com"
  },
  {
    "nome": "Helena",
    "sobrenome": "Pietra Francisca Nascimento",
    "empresa": "EBAC",
    "endereco": "Rua General Martiniano Espínola",
    "numero": "337",
    "pais": "Brasil",
    "cidade": "São Paulo",
    "estado": "São Paulo",
    "cep": "02319-020",
    "telefone": "(11) 99340-1163",
    "email": "helenapietrafranciscanascimento..helenapietrafranciscanascimento@sp.gov.br"
  },
  {
    "nome": "Henry",
    "sobrenome": "Felipe Samuel de Paula",
    "empresa": "EBAC",
    "endereco": "Rua Aquiles Paraguassu",
    "numero": "263",
    "pais": "Brasil",
    "cidade": "Porto Velho",
    "estado": "Rondônia",
    "cep": "76810-251",
    "telefone": "(69) 98404-0867",
    "email": "henryfelipesamueldepaula-98@greenbikeshop.com.br"
  }
]
